{"_t": 1776876754.6398246, "_k": "/epcis/249500430/communes?fields=nom%2Ccode%2Cpopulation&format=json", "value": [{"nom": "Arronville", "code": "95023", "population": 618}, {"nom": "Auvers-sur-Oise", "code": "95039", "population": 6863}, {"nom": "Butry-sur-Oise", "code": "95120", "population": 2252}, {"nom": "Ennery", "code": "95211", "population": 2243}, {"nom": "Épiais-Rhus", "code": "95213", "population": 603}, {"nom": "Frouville", "code": "95258", "population": 347}, {"nom": "Génicourt", "code": "95271", "population": 514}, {"nom": "Hédouville", "code": "95304", "population": 278}, {"nom": "Hérouville-en-Vexin", "code": "95308", "population": 584}, {"nom": "Labbeville", "code": "95328", "population": 641}, {"nom": "Livilliers", "code": "95341", "population": 389}, {"nom": "Menouville", "code": "95387", "population": 62}, {"nom": "Nesles-la-Vallée", "code": "95446", "population": 1842}, {"nom": "Vallangoujard", "code": "95627", "population": 625}, {"nom": "Valmondois", "code": "95628", "population": 1208}]}